opengrep/__init__.py
opengrep/main.py
opengrep-0.0.8.dist-info/METADATA
opengrep-0.0.8.dist-info/WHEEL
opengrep-0.0.8.dist-info/entry_points.txt
opengrep-0.0.8.dist-info/top_level.txt
opengrep-0.0.8.dist-info/RECORD
